{"configuration": {"menu": {"position": {"anchor": {"x": 1, "y": 1}, "pivot": {"x": 1, "y": 1}}}, "score": {"position": {"anchor": {"x": 0, "y": 1}, "pivot": {"x": 0, "y": 1}}, "text": {"horizontal": "left", "vertical": "top"}}, "combo": {"position": {"anchor": {"x": 0.9, "y": 0.5}, "pivot": {"x": 0.5, "y": 0.5}}}, "judgement": {"position": {"anchor": {"x": 0.5, "y": 0.25}, "pivot": {"x": 0.5, "y": 0}}, "text": {"horizontal": "center", "vertical": "bottom"}}}, "entities": [{"archetype": 5}, {"archetype": 3}, {"archetype": 4}, {"archetype": 2, "data": {"index": 0, "values": [1.0, 0.0, 0.0, 1.5, 0.0, 0.7, 0.1, 1.0]}}, {"archetype": 0, "data": {"index": 0, "values": [1.0, 0.5, 0.5, 1.5, 45.0, 0.7, 0.1, 1.0]}}, {"archetype": 2, "data": {"index": 0, "values": [2.0, 0.0, 0.0, 1.5, 0.0, 0.7, 0.1, 1.0]}}, {"archetype": 0, "data": {"index": 0, "values": [2.0, -0.5, -0.5, 1.5, 225.0, 0.7, 0.1, 1.0]}}, {"archetype": 0, "data": {"index": 0, "values": [3.0, 0.5, 0.0, 1.5, 90.0, 0.7, 0.1, 1.0]}}, {"archetype": 0, "data": {"index": 0, "values": [3.0, -0.5, 0.0, 1.5, 270.0, 0.7, 0.1, 1.0]}}, {"archetype": 1, "data": {"index": 0, "values": [3.5, 1.0, 0.5, 1.5, 135.0, 0.7, 0.1, 1.0]}}, {"archetype": 1, "data": {"index": 0, "values": [3.525, 0.95, 0.475, 1.5, 135.0, 0.7, 0.1, 1.0]}}, {"archetype": 1, "data": {"index": 0, "values": [3.55, 0.9, 0.45, 1.5, 135.0, 0.7, 0.1, 1.0]}}, {"archetype": 1, "data": {"index": 0, "values": [3.575, 0.85, 0.425, 1.5, 135.0, 0.7, 0.1, 1.0]}}, {"archetype": 1, "data": {"index": 0, "values": [3.6, 0.8, 0.4, 1.5, 135.0, 0.7, 0.1, 1.0]}}, {"archetype": 1, "data": {"index": 0, "values": [3.625, 0.75, 0.375, 1.5, 135.0, 0.7, 0.1, 1.0]}}, {"archetype": 1, "data": {"index": 0, "values": [3.65, 0.7, 0.35, 1.5, 135.0, 0.7, 0.1, 1.0]}}, {"archetype": 1, "data": {"index": 0, "values": [3.675, 0.65, 0.325, 1.5, 135.0, 0.7, 0.1, 1.0]}}, {"archetype": 1, "data": {"index": 0, "values": [3.7, 0.6, 0.3, 1.5, 135.0, 0.7, 0.1, 1.0]}}, {"archetype": 1, "data": {"index": 0, "values": [3.725, 0.55, 0.275, 1.5, 135.0, 0.7, 0.1, 1.0]}}, {"archetype": 1, "data": {"index": 0, "values": [3.75, 0.5, 0.25, 1.5, 135.0, 0.7, 0.1, 1.0]}}, {"archetype": 1, "data": {"index": 0, "values": [3.775, 0.45, 0.225, 1.5, 135.0, 0.7, 0.1, 1.0]}}, {"archetype": 1, "data": {"index": 0, "values": [3.8, 0.4, 0.2, 1.5, 135.0, 0.7, 0.1, 1.0]}}, {"archetype": 1, "data": {"index": 0, "values": [3.825, 0.35, 0.175, 1.5, 135.0, 0.7, 0.1, 1.0]}}, {"archetype": 1, "data": {"index": 0, "values": [3.85, 0.3, 0.15, 1.5, 135.0, 0.7, 0.1, 1.0]}}, {"archetype": 1, "data": {"index": 0, "values": [3.875, 0.25, 0.125, 1.5, 135.0, 0.7, 0.1, 1.0]}}, {"archetype": 1, "data": {"index": 0, "values": [3.9, 0.2, 0.1, 1.5, 135.0, 0.7, 0.1, 1.0]}}, {"archetype": 1, "data": {"index": 0, "values": [3.925, 0.15, 0.075, 1.5, 135.0, 0.7, 0.1, 1.0]}}, {"archetype": 1, "data": {"index": 0, "values": [3.95, 0.1, 0.05, 1.5, 135.0, 0.7, 0.1, 1.0]}}, {"archetype": 1, "data": {"index": 0, "values": [3.975, 0.05, 0.025, 1.5, 135.0, 0.7, 0.1, 1.0]}}, {"archetype": 1, "data": {"index": 0, "values": [4.0, 0.0, 0.0, 1.5, 135.0, 0.7, 0.1, 1.0]}}, {"archetype": 1, "data": {"index": 0, "values": [3.5, -1.0, -0.5, 1.5, 315.0, 0.7, 0.1, 1.0]}}, {"archetype": 1, "data": {"index": 0, "values": [3.525, -0.95, -0.475, 1.5, 315.0, 0.7, 0.1, 1.0]}}, {"archetype": 1, "data": {"index": 0, "values": [3.55, -0.9, -0.45, 1.5, 315.0, 0.7, 0.1, 1.0]}}, {"archetype": 1, "data": {"index": 0, "values": [3.575, -0.85, -0.425, 1.5, 315.0, 0.7, 0.1, 1.0]}}, {"archetype": 1, "data": {"index": 0, "values": [3.6, -0.8, -0.4, 1.5, 315.0, 0.7, 0.1, 1.0]}}, {"archetype": 1, "data": {"index": 0, "values": [3.625, -0.75, -0.375, 1.5, 315.0, 0.7, 0.1, 1.0]}}, {"archetype": 1, "data": {"index": 0, "values": [3.65, -0.7, -0.35, 1.5, 315.0, 0.7, 0.1, 1.0]}}, {"archetype": 1, "data": {"index": 0, "values": [3.675, -0.65, -0.325, 1.5, 315.0, 0.7, 0.1, 1.0]}}, {"archetype": 1, "data": {"index": 0, "values": [3.7, -0.6, -0.3, 1.5, 315.0, 0.7, 0.1, 1.0]}}, {"archetype": 1, "data": {"index": 0, "values": [3.725, -0.55, -0.275, 1.5, 315.0, 0.7, 0.1, 1.0]}}, {"archetype": 1, "data": {"index": 0, "values": [3.75, -0.5, -0.25, 1.5, 315.0, 0.7, 0.1, 1.0]}}, {"archetype": 1, "data": {"index": 0, "values": [3.775, -0.45, -0.225, 1.5, 315.0, 0.7, 0.1, 1.0]}}, {"archetype": 1, "data": {"index": 0, "values": [3.8, -0.4, -0.2, 1.5, 315.0, 0.7, 0.1, 1.0]}}, {"archetype": 1, "data": {"index": 0, "values": [3.825, -0.35, -0.175, 1.5, 315.0, 0.7, 0.1, 1.0]}}, {"archetype": 1, "data": {"index": 0, "values": [3.85, -0.3, -0.15, 1.5, 315.0, 0.7, 0.1, 1.0]}}, {"archetype": 1, "data": {"index": 0, "values": [3.875, -0.25, -0.125, 1.5, 315.0, 0.7, 0.1, 1.0]}}, {"archetype": 1, "data": {"index": 0, "values": [3.9, -0.2, -0.1, 1.5, 315.0, 0.7, 0.1, 1.0]}}, {"archetype": 1, "data": {"index": 0, "values": [3.925, -0.15, -0.075, 1.5, 315.0, 0.7, 0.1, 1.0]}}, {"archetype": 1, "data": {"index": 0, "values": [3.95, -0.1, -0.05, 1.5, 315.0, 0.7, 0.1, 1.0]}}, {"archetype": 1, "data": {"index": 0, "values": [3.975, -0.05, -0.025, 1.5, 315.0, 0.7, 0.1, 1.0]}}, {"archetype": 1, "data": {"index": 0, "values": [4.0, -0.0, -0.0, 1.5, 315.0, 0.7, 0.1, 1.0]}}, {"archetype": 0, "data": {"index": 0, "values": [5.0, 0.0, 0.0, 1.5, 0.0, 0.7, 0.1, 2.0]}}, {"archetype": 0, "data": {"index": 0, "values": [5.0, 0.0, 0.0, 1.5, 180.0, 0.7, 0.1, 2.0]}}, {"archetype": 2, "data": {"index": 0, "values": [6.0, 0.0, 0.0, 1.5, 90.0, 0.7, 0.1, 0.8]}}, {"archetype": 2, "data": {"index": 0, "values": [6.5, 0.0, 0.0, 1.5, 180.0, 0.7, 0.1, 1.0]}}, {"archetype": 2, "data": {"index": 0, "values": [7.0, 0.0, 0.0, 1.5, 270.0, 0.7, 0.1, 1.2]}}, {"archetype": 2, "data": {"index": 0, "values": [7.5, 0.0, 0.0, 1.5, 0.0, 0.7, 0.1, 1.4]}}, {"archetype": 2, "data": {"index": 0, "values": [8.0, 0.0, 0.0, 1.5, 90.0, 0.7, 0.1, 1.6]}}, {"archetype": 0, "data": {"index": 0, "values": [9.0, 0.0, 0.0, 1.5, 90.0, 0.7, 0.1, 1.0, 10.0]}}, {"archetype": 0, "data": {"index": 0, "values": [9.5, 0.0, 0.0, 1.5, 90.0, 0.7, 0.1, 1.0, 10.0]}}, {"archetype": 0, "data": {"index": 0, "values": [10.0, 0.0, 0.0, 1.5, 90.0, 0.7, 0.1, 1.0, 10.0]}}, {"archetype": 0, "data": {"index": 0, "values": [10.5, 0.0, 0.0, 1.5, 90.0, 0.7, 0.1, 1.0, 10.0]}}, {"archetype": 0, "data": {"index": 0, "values": [11.0, 0.0, 0.0, 1.2, 90.0, 3.0, 2.0, 1.5]}}, {"archetype": 1, "data": {"index": 0, "values": [11.5, 0.0, 0.0, 1.5, 45.0, 0.7, 0.1, 1.0]}}, {"archetype": 1, "data": {"index": 0, "values": [11.75, 0.25, 0.25, 1.5, 45.0, 0.7, 0.1, 1.0]}}, {"archetype": 2, "data": {"index": 0, "values": [12.0, 0.5, 0.5, 1.5, 45.0, 0.7, 0.1, 1.0]}}, {"archetype": 1, "data": {"index": 0, "values": [12.5, 0.0, 0.0, 1.5, 135.0, 0.7, 0.1, 1.0]}}, {"archetype": 1, "data": {"index": 0, "values": [12.75, -0.25, 0.25, 1.5, 135.0, 0.7, 0.1, 1.0]}}, {"archetype": 2, "data": {"index": 0, "values": [13.0, -0.5, 0.5, 1.5, 135.0, 0.7, 0.1, 1.0]}}, {"archetype": 1, "data": {"index": 0, "values": [13.5, 0.0, 0.0, 1.5, 225.0, 0.7, 0.1, 1.0]}}, {"archetype": 1, "data": {"index": 0, "values": [13.75, -0.25, -0.25, 1.5, 225.0, 0.7, 0.1, 1.0]}}, {"archetype": 2, "data": {"index": 0, "values": [14.0, -0.5, -0.5, 1.5, 225.0, 0.7, 0.1, 1.0]}}, {"archetype": 1, "data": {"index": 0, "values": [14.5, 0.0, 0.0, 1.5, 315.0, 0.7, 0.1, 1.0]}}, {"archetype": 1, "data": {"index": 0, "values": [14.75, 0.25, -0.25, 1.5, 315.0, 0.7, 0.1, 1.0]}}, {"archetype": 2, "data": {"index": 0, "values": [15.0, 0.5, -0.5, 1.5, 315.0, 0.7, 0.1, 1.0]}}], "archetypes": [{"script": 0, "input": true}, {"script": 3, "input": true}, {"script": 2, "input": true}, {"script": 6, "input": false}, {"script": 5, "input": false}, {"script": 1, "input": false}], "scripts": [{"shouldSpawn": {"index": 298, "order": 0}, "updateParallel": {"index": 192, "order": 0}, "touch": {"index": 127, "order": 0}, "initialize": {"index": 61, "order": 0}}, {"updateSequential": {"index": 1, "order": 0}, "initialize": {"index": 0, "order": 0}}, {"shouldSpawn": {"index": 298, "order": 0}, "updateParallel": {"index": 219, "order": 0}, "touch": {"index": 145, "order": 0}, "initialize": {"index": 241, "order": 0}}, {"shouldSpawn": {"index": 298, "order": 0}, "updateParallel": {"index": 282, "order": 0}, "touch": {"index": 56, "order": 0}, "initialize": {"index": 61, "order": 0}}, {"updateParallel": {"index": 23, "order": 0}, "initialize": {"index": 215, "order": 0}}, {"initialize": {"index": 0, "order": 0}, "shouldSpawn": {"index": 227, "order": 0}, "touch": {"index": 251, "order": 100.0}}, {"initialize": {"index": 0, "order": 0}, "shouldSpawn": {"index": 227, "order": 0}, "touch": {"index": 132, "order": 0}}], "nodes": [{"value": 0}, {"value": 1.0}, {"value": 2.0}, {"value": 3}, {"value": 4.0}, {"value": 5}, {"value": 6.0}, {"value": 0.5}, {"value": 8}, {"value": 1.5}, {"value": 7}, {"value": 1.25}, {"value": 10.0}, {"value": 13.0}, {"func": "And", "args": [300, 223]}, {"value": 21}, {"value": 22}, {"value": 23.0}, {"func": "Less", "args": [141, 123]}, {"value": 41001.0}, {"func": "Multiply", "args": [317, 320]}, {"func": "Multiply", "args": [278, 292]}, {"func": "Get", "args": [16, 8]}, {"func": "If", "args": [155, 24, 1]}, {"func": "Draw", "args": [146, 69, 288, 143, 290, 207, 88, 97, 86, 46, 232]}, {"func": "Not", "args": [314]}, {"func": "Subtract", "args": [136, 102]}, {"func": "Set", "args": [17, 0, 1]}, {"func": "Subtract", "args": [252, 79]}, {"func": "Multiply", "args": [85, 0]}, {"value": 100.0}, {"value": 101.0}, {"func": "Cos", "args": [144]}, {"func": "Or", "args": [178, 60]}, {"func": "Add", "args": [314, 173]}, {"func": "Get", "args": [16, 6]}, {"func": "Set", "args": [15, 5, 0]}, {"func": "Subtract", "args": [79, 158]}, {"func": "Add", "args": [176, 226]}, {"func": "Add", "args": [91, 226]}, {"func": "LessOr", "args": [234, 294]}, {"value": 180.0}, {"func": "Divide", "args": [20, 2]}, {"func": "Cos", "args": [125]}, {"value": 200.0}, {"func": "Draw", "args": [19, 316, 98, 280, 54, 159, 309, 187, 114, 39, 263]}, {"func": "Get", "args": [15, 10]}, {"func": "Set", "args": [15, 4, 1]}, {"func": "Add", "args": [83, 67]}, {"func": "Add", "args": [48, 281]}, {"func": "Multiply", "args": [142, 52]}, {"func": "Add", "args": [48, 229]}, {"func": "Divide", "args": [312, 2]}, {"func": "Add", "args": [80, 274]}, {"func": "Add", "args": [195, 179]}, {"func": "Subtract", "args": [167, 28]}, {"func": "And", "args": [242, 78]}, {"func": "Add", "args": [235, 311]}, {"func": "Not", "args": [277]}, {"func": "Sin", "args": [94]}, {"func": "Get", "args": [15, 5]}, {"func": "Execute", "args": [153, 171, 126, 81, 133]}, {"func": "Add", "args": [130, 274]}, {"func": "Multiply", "args": [273, 150]}, {"func": "Multiply", "args": [60, 286]}, {"func": "Get", "args": [17, 0]}, {"func": "Multiply", "args": [107, 320]}, {"func": "Multiply", "args": [273, 175]}, {"func": "Divide", "args": [146, 2]}, {"func": "Subtract", "args": [34, 194]}, {"func": "Add", "args": [149, 179]}, {"value": 0.05}, {"func": "Subtract", "args": [136, 63]}, {"func": "Multiply", "args": [199, 151]}, {"func": "Multiply", "args": [196, 254]}, {"func": "Subtract", "args": [93, 319]}, {"func": "Add", "args": [44, 226]}, {"func": "Multiply", "args": [283, 168]}, {"func": "Execute", "args": [198, 27, 193, 271, 218]}, {"func": "Get", "args": [1, 0]}, {"func": "Add", "args": [96, 50]}, {"func": "Set", "args": [15, 3, 0]}, {"func": "Add", "args": [314, 186]}, {"func": "Add", "args": [96, 259]}, {"value": 21005.0}, {"func": "Sin", "args": [182]}, {"func": "Add", "args": [103, 165]}, {"func": "Set", "args": [17, 0, 117]}, {"func": "Add", "args": [103, 147]}, {"func": "Get", "args": [16, 1]}, {"func": "Draw", "args": [164, 121, 53, 189, 265, 293, 70, 222, 119, 160, 263]}, {"func": "Multiply", "args": [30, 320]}, {"func": "Get", "args": [31, 5]}, {"func": "Add", "args": [170, 108]}, {"func": "Get", "args": [15, 2]}, {"func": "Multiply", "args": [220, 254]}, {"func": "Add", "args": [303, 184]}, {"func": "Subtract", "args": [82, 194]}, {"func": "Add", "args": [195, 274]}, {"func": "Cos", "args": [109]}, {"func": "Add", "args": [130, 201]}, {"func": "Subtract", "args": [89, 92]}, {"func": "Multiply", "args": [273, 106]}, {"func": "Add", "args": [178, 262]}, {"func": "Execute", "args": [305, 198, 87, 205, 271, 258]}, {"func": "Multiply", "args": [237, 156]}, {"func": "Divide", "args": [314, 2]}, {"func": "Multiply", "args": [172, 286]}, {"func": "Multiply", "args": [43, 42]}, {"func": "Add", "args": [0, 182]}, {"func": "Add", "args": [89, 179]}, {"value": 0.13999999999999999}, {"func": "Get", "args": [1, 4]}, {"func": "Get", "args": [16, 3]}, {"func": "Add", "args": [169, 274]}, {"func": "Get", "args": [31, 1]}, {"func": "Add", "args": [178, 212]}, {"func": "JudgeSimple", "args": [79, 128, 71, 135, 276]}, {"func": "And", "args": [275, 204]}, {"func": "Add", "args": [149, 274]}, {"func": "Draw", "args": [84, 188, 268, 75, 250, 137, 139, 246, 190, 38, 263]}, {"func": "Subtract", "args": [62, 50]}, {"func": "Set", "args": [15, 3, 134]}, {"func": "Multiply", "args": [276, 320]}, {"func": "Add", "args": [266, 236]}, {"func": "Add", "args": [0, 144]}, {"func": "Set", "args": [15, 1, 225]}, {"func": "And", "args": [269, 148]}, {"func": "Add", "args": [252, 112]}, {"func": "Divide", "args": [107, 2]}, {"func": "Add", "args": [89, 105]}, {"func": "Divide", "args": [66, 2]}, {"func": "Set", "args": [0, 0, 0]}, {"func": "Set", "args": [15, 4, 0]}, {"func": "Multiply", "args": [238, 151]}, {"value": 0.1}, {"func": "Add", "args": [100, 299]}, {"func": "Subtract", "args": [224, 319]}, {"func": "Multiply", "args": [85, 254]}, {"func": "Add", "args": [124, 239]}, {"func": "Play", "args": [4, 157]}, {"func": "Subtract", "args": [128, 79]}, {"func": "Sin", "args": [0]}, {"func": "Subtract", "args": [34, 244]}, {"func": "Add", "args": [202, 94]}, {"func": "And", "args": [14, 247]}, {"func": "Get", "args": [15, 0]}, {"func": "Multiply", "args": [272, 129]}, {"func": "And", "args": [118, 104]}, {"func": "Add", "args": [96, 217]}, {"func": "Divide", "args": [315, 2]}, {"func": "Get", "args": [16, 10]}, {"func": "Power", "args": [233, 7]}, {"func": "Set", "args": [15, 2, 174]}, {"func": "Subtract", "args": [252, 167]}, {"func": "LessOr", "args": [37, 226]}, {"func": "Divide", "args": [28, 167]}, {"value": 0.02}, {"func": "Get", "args": [15, 8]}, {"func": "Subtract", "args": [110, 217]}, {"func": "Add", "args": [22, 226]}, {"func": "Power", "args": [240, 2]}, {"value": 1001.0}, {"value": 1003.0}, {"value": 1005.0}, {"func": "Multiply", "args": [272, 131]}, {"func": "Multiply", "args": [32, 0]}, {"func": "Get", "args": [16, 5]}, {"func": "Subtract", "args": [94, 1]}, {"func": "Add", "args": [303, 217]}, {"func": "Add", "args": [130, 211]}, {"func": "Set", "args": [15, 0, 73]}, {"func": "Get", "args": [15, 6]}, {"func": "Multiply", "args": [272, 210]}, {"func": "Radian", "args": [291]}, {"func": "Divide", "args": [317, 2]}, {"func": "Subtract", "args": [22, 135]}, {"func": "Multiply", "args": [64, 320]}, {"func": "Get", "args": [15, 4]}, {"func": "Multiply", "args": [272, 68]}, {"func": "LessOr", "args": [234, 135]}, {"func": "And", "args": [206, 208]}, {"func": "Add", "args": [230, 94]}, {"func": "And", "args": [285, 47]}, {"func": "Multiply", "args": [270, 156]}, {"func": "Cos", "args": [94]}, {"func": "Multiply", "args": [272, 318]}, {"func": "Subtract", "args": [110, 50]}, {"func": "Subtract", "args": [93, 264]}, {"func": "Subtract", "args": [62, 217]}, {"func": "Add", "args": [124, 191]}, {"func": "Multiply", "args": [43, 150]}, {"func": "Execute", "args": [45, 209, 261, 295]}, {"func": "Play", "args": [1, 157]}, {"func": "Multiply", "args": [142, 131]}, {"func": "Add", "args": [303, 50]}, {"func": "Sin", "args": [144]}, {"func": "LessOr", "args": [152, 146]}, {"func": "Set", "args": [15, 3, 1]}, {"value": 0.4}, {"func": "Multiply", "args": [43, 175]}, {"func": "Subtract", "args": [297, 138]}, {"func": "Radian", "args": [0]}, {"func": "Get", "args": [12, 2]}, {"func": "LessOr", "args": [234, 276]}, {"func": "Play", "args": [65, 157]}, {"func": "Less", "args": [141, 296]}, {"func": "Subtract", "args": [82, 244]}, {"func": "Set", "args": [15, 5, 1]}, {"func": "Draw", "args": [162, 121, 53, 189, 265, 293, 70, 222, 119, 160, 263]}, {"func": "Divide", "args": [177, 2]}, {"func": "Subtract", "args": [166, 74]}, {"func": "Multiply", "args": [142, 210]}, {"func": "Multiply", "args": [99, 42]}, {"func": "Sin", "args": [125]}, {"func": "Set", "args": [15, 8, 79]}, {"func": "And", "args": [228, 197]}, {"func": "Multiply", "args": [142, 68]}, {"func": "Spawn", "args": [4, 163, 135, 9, 130, 96, 146, 146, 76]}, {"func": "Execute", "args": [45, 90, 120, 306, 181, 33]}, {"func": "Cos", "args": [182]}, {"func": "Multiply", "args": [111, 151]}, {"func": "Subtract", "args": [302, 50]}, {"func": "GreaterOr", "args": [257, 9]}, {"func": "Add", "args": [170, 200]}, {"func": "Divide", "args": [154, 30]}, {"func": "Get", "args": [15, 1]}, {"func": "Equal", "args": [203, 2]}, {"func": "Not", "args": [178]}, {"func": "Multiply", "args": [99, 150]}, {"func": "Radian", "args": [41]}, {"func": "Multiply", "args": [294, 320]}, {"func": "Subtract", "args": [1, 283]}, {"func": "Add", "args": [253, 161]}, {"func": "Abs", "args": [141]}, {"func": "Multiply", "args": [196, 0]}, {"func": "Multiply", "args": [214, 175]}, {"func": "Multiply", "args": [185, 113]}, {"value": 0.32000000000000006}, {"func": "Multiply", "args": [43, 106]}, {"func": "Subtract", "args": [303, 267]}, {"func": "Execute", "args": [153, 171, 122, 126, 133, 36]}, {"func": "And", "args": [275, 40]}, {"func": "Multiply", "args": [214, 42]}, {"func": "Multiply", "args": [142, 129]}, {"func": "Add", "args": [100, 213]}, {"func": "Subtract", "args": [224, 264]}, {"func": "Execute", "args": [47, 27, 140, 271, 256]}, {"func": "Add", "args": [83, 284]}, {"func": "Add", "args": [266, 243]}, {"func": "Add", "args": [249, 239]}, {"func": "And", "args": [279, 307]}, {"func": "Get", "args": [16, 0]}, {"func": "Power", "args": [101, 2]}, {"func": "Add", "args": [221, 21]}, {"func": "Subtract", "args": [245, 102]}, {"func": "Spawn", "args": [4, 164, 135, 9, 130, 96, 146, 146, 76]}, {"func": "Get", "args": [31, 13]}, {"func": "Spawn", "args": [4, 162, 135, 9, 130, 96, 146, 146, 76]}, {"func": "Add", "args": [29, 95]}, {"func": "Add", "args": [89, 274]}, {"func": "And", "args": [18, 47]}, {"func": "Multiply", "args": [142, 318]}, {"func": "Clamp", "args": [308, 0, 1]}, {"func": "Multiply", "args": [214, 150]}, {"func": "Add", "args": [80, 179]}, {"func": "Add", "args": [96, 57]}, {"func": "Get", "args": [31, 6]}, {"func": "Add", "args": [249, 191]}, {"func": "And", "args": [58, 115]}, {"func": "Multiply", "args": [59, 113]}, {"func": "Spawn", "args": [4, 19, 135, 2, 89, 303, 146, 146, 76]}, {"func": "Cos", "args": [0]}, {"func": "Sin", "args": [109]}, {"func": "Multiply", "args": [272, 52]}, {"func": "And", "args": [25, 197]}, {"value": 0.12}, {"func": "Get", "args": [0, 0]}, {"value": 0.16000000000000003}, {"func": "And", "args": [115, 58]}, {"func": "Subtract", "args": [260, 217]}, {"func": "Multiply", "args": [99, 106]}, {"func": "Execute", "args": [45, 289, 183, 295]}, {"func": "Divide", "args": [37, 226]}, {"func": "Multiply", "args": [273, 42]}, {"func": "Less", "args": [141, 231]}, {"func": "Add", "args": [1, 77]}, {"func": "Add", "args": [167, 6]}, {"func": "Add", "args": [116, 165]}, {"func": "Draw", "args": [163, 121, 53, 189, 265, 293, 70, 222, 119, 160, 263]}, {"func": "Add", "args": [116, 147]}, {"func": "Get", "args": [16, 4]}, {"func": "Clamp", "args": [304, 0, 1]}, {"func": "Subtract", "args": [302, 217]}, {"value": 0.08}, {"func": "Or", "args": [314, 178]}, {"func": "Multiply", "args": [135, 320]}, {"func": "Multiply", "args": [220, 0]}, {"func": "LessOr", "args": [28, 287]}, {"func": "Multiply", "args": [99, 175]}, {"func": "And", "args": [216, 180]}, {"func": "Add", "args": [248, 281]}, {"func": "Add", "args": [130, 179]}, {"func": "Get", "args": [16, 2]}, {"func": "Divide", "args": [55, 167]}, {"func": "Set", "args": [0, 0, 1]}, {"func": "Draw", "args": [84, 313, 310, 255, 301, 26, 49, 72, 51, 38, 263]}, {"func": "Play", "args": [5, 157]}, {"func": "Divide", "args": [55, 35]}, {"func": "Add", "args": [169, 179]}, {"func": "Add", "args": [248, 229]}, {"func": "Multiply", "args": [32, 254]}, {"func": "Multiply", "args": [146, 320]}, {"func": "Subtract", "args": [245, 63]}, {"func": "Get", "args": [15, 3]}, {"func": "Multiply", "args": [314, 320]}, {"func": "Subtract", "args": [260, 50]}, {"func": "Multiply", "args": [11, 314]}, {"func": "Divide", "args": [64, 2]}, {"func": "Multiply", "args": [214, 106]}, {"value": -1.0}]}